JMeterClasses.py
JMeterLib.py
robotframework_jmeterlib-1.0.data/data/Doc/JMeterLib.html
robotframework_jmeterlib-1.0.data/data/Scripts/jmeterLibExample.txt
robotframework_jmeterlib-1.0.dist-info/METADATA
robotframework_jmeterlib-1.0.dist-info/WHEEL
robotframework_jmeterlib-1.0.dist-info/top_level.txt
robotframework_jmeterlib-1.0.dist-info/RECORD
