Metadata-Version: 2.1
Name: robotframework-jmeterlib
Version: 1.0
Summary: Robot Framework JMeter Library
Home-page: https://github.com/kowalpy/Robot-Framework-JMeter-Library
Author: Satish
Author-email: emaseaccela@gmail.com
License: none
